pandera_report/__init__.py
pandera_report/options.py
pandera_report/parser.py
pandera_report/validator.py
pandera_report/version.py
pandera_report-0.1.2.dist-info/LICENSE.md
pandera_report-0.1.2.dist-info/METADATA
pandera_report-0.1.2.dist-info/WHEEL
pandera_report-0.1.2.dist-info/RECORD
