Metadata-Version: 2.1
Name: pandera-report
Version: 0.1.2
Summary: Pandera Report for row-based reporting by using the power of pandera.
License: MIT
Author: Pit Nahrstedt
Author-email: pit.nahrstedt@outlook.de
Requires-Python: >=3.9,<3.13
Classifier: Development Status :: 4 - Beta
Classifier: Intended Audience :: Science/Research
Classifier: License :: OSI Approved :: MIT License
Classifier: Operating System :: OS Independent
Classifier: Programming Language :: Python
Classifier: Programming Language :: Python :: 3
Classifier: Programming Language :: Python :: 3.9
Classifier: Programming Language :: Python :: 3.10
Classifier: Programming Language :: Python :: 3.11
Classifier: Programming Language :: Python :: 3.12
Classifier: Topic :: Scientific/Engineering
Requires-Dist: numpy (>=1.26.4,<2.0.0)
Requires-Dist: pandas (>=2.2.3,<3.0.0)
Requires-Dist: pandera (>=0.20.4,<0.21.0)
Project-URL: Homepage, https://github.com/Luanee/pandera-report
